streamlit_highcharts/__init__.py
streamlit_highcharts/frontend/index.html
streamlit_highcharts/frontend/main.js
streamlit_highcharts/frontend/streamlit-component-lib.js
streamlit_highcharts/frontend/style.css
streamlit_highcharts-0.2.0.dist-info/LICENSE
streamlit_highcharts-0.2.0.dist-info/METADATA
streamlit_highcharts-0.2.0.dist-info/WHEEL
streamlit_highcharts-0.2.0.dist-info/top_level.txt
streamlit_highcharts-0.2.0.dist-info/RECORD
