Metadata-Version: 2.1
Name: streamlit-highcharts
Version: 0.2.0
Summary: Simple wrapper for Highcharts JS libs
Author: Anthony Alteirac
Author-email: anthony@alteirac.com
Requires-Python: >=3.7
License-File: LICENSE
Requires-Dist: streamlit >=1.2
Requires-Dist: jinja2
